aio_usb_hotplug/__init__.py
aio_usb_hotplug/__main__.py
aio_usb_hotplug/errors.py
aio_usb_hotplug/py.typed
aio_usb_hotplug/task.py
aio_usb_hotplug/version.py
aio_usb_hotplug/backends/__init__.py
aio_usb_hotplug/backends/autodetect.py
aio_usb_hotplug/backends/base.py
aio_usb_hotplug/backends/dummy.py
aio_usb_hotplug/backends/pyusb.py
aio_usb_hotplug-7.0.0.dist-info/METADATA
aio_usb_hotplug-7.0.0.dist-info/WHEEL
aio_usb_hotplug-7.0.0.dist-info/licenses/LICENSE
aio_usb_hotplug-7.0.0.dist-info/RECORD
