Metadata-Version: 2.4
Name: aio-usb-hotplug
Version: 7.0.0
Summary: Asynchronous generators yielding detected hotplug events on the USB buses
Project-URL: Homepage, https://github.com/ntamas/aio-usb-hotplug/
Project-URL: Repository, https://github.com/ntamas/aio-usb-hotplug/
Author-email: Tamas Nepusz <tamas@collmot.com>
License-Expression: MIT
License-File: LICENSE
Requires-Python: >=3.9
Requires-Dist: anyio>=4.9.0
Requires-Dist: pyudev>=0.24.3; sys_platform == 'linux'
Requires-Dist: pyusb>=1.3.1
